[
    {
        "title": "เมืองหลวงของประเทศไทยคืออะไร?",
        "options": ["เชียงใหม่", "กรุงเทพฯ", "ภูเก็ต", "พัทยา"],
        "answer": 2
    },
    {
        "title": "2 + 3 เท่ากับเท่าไหร่?",
        "options": ["4", "5", "6", "7"],
        "answer": 2
    },
    {
        "title": "สีของท้องฟ้าปกติในตอนกลางวันคือสีอะไร?",
        "options": ["แดง", "เหลือง", "น้ำเงิน", "เขียว"],
        "answer": 3
    },
    {
        "title": "สัตว์ชนิดใดที่ไม่ใช่สัตว์เลี้ยงลูกด้วยนม?",
        "options": ["แมว", "นก", "ช้าง", "สุนัข"],
        "answer": 2
    },
    {
        "title": "1 กิโลเมตรมีกี่เมตร?",
        "options": ["100", "1000", "10,000", "1,000,000"],
        "answer": 2
    },
    {
        "title": "ประเทศใดอยู่ในทวีปยุโรป?",
        "options": ["ไทย", "สหรัฐอเมริกา", "เยอรมนี", "ญี่ปุ่น"],
        "answer": 3
    },
    {
        "title": "ในระบบสุริยะ ดาวเคราะห์ดวงใดอยู่ใกล้ดวงอาทิตย์ที่สุด?",
        "options": ["โลก", "ดาวศุกร์", "ดาวพุธ", "ดาวอังคาร"],
        "answer": 3
    },
    {
        "title": "ธาตุเคมีที่มีสัญลักษณ์ว่า 'O' คืออะไร?",
        "options": ["ออกซิเจน", "ไฮโดรเจน", "นีออน", "ไนโตรเจน"],
        "answer": 1
    },
    {
        "title": "ประเทศไทยมีจังหวัดทั้งหมดกี่จังหวัด?",
        "options": ["76", "77", "78", "79"],
        "answer": 2
    },
    {
        "title": "ในนิทานเรื่อง 'หนูน้อยหมวกแดง' ใครเป็นผู้ร้าย?",
        "options": ["หมาป่า", "คุณยาย", "หนูน้อยหมวกแดง", "ลุงพราน"],
        "answer": 1
    },
    {
        "title": "10 x 10 เท่ากับเท่าไหร่?",
        "options": ["10", "100", "1000", "10000"],
        "answer": 2
    },
    {
        "title": "ภาษาใดที่ใช้ในประเทศญี่ปุ่น?",
        "options": ["เกาหลี", "ญี่ปุ่น", "จีน", "อังกฤษ"],
        "answer": 2
    },
    {
        "title": "วันที่ 25 ธันวาคม เป็นวันสำคัญอะไร?",
        "options": ["วันปีใหม่", "วันคริสต์มาส", "วันฮาโลวีน", "วันสงกรานต์"],
        "answer": 2
    },
    {
        "title": "ดาวเคราะห์ดวงใดใหญ่ที่สุดในระบบสุริยะ?",
        "options": ["ดาวพฤหัส", "ดาวเสาร์", "ดาวอังคาร", "โลก"],
        "answer": 1
    },
    {
        "title": "ธงชาติของประเทศญี่ปุ่นมีสีอะไร?",
        "options": ["แดง-ขาว", "น้ำเงิน-เหลือง", "เขียว-ขาว", "ดำ-แดง"],
        "answer": 1
    },
    {
        "title": "กีฬาโอลิมปิกจัดขึ้นทุก ๆ กี่ปี?",
        "options": ["2 ปี", "3 ปี", "4 ปี", "5 ปี"],
        "answer": 3
    },
    {
        "title": "พืชชนิดใดเป็นพืชล้มลุก?",
        "options": ["มะม่วง", "ต้นข้าว", "มะพร้าว", "ไผ่"],
        "answer": 2
    },
    {
        "title": "แม่น้ำที่ยาวที่สุดในโลกคือแม่น้ำอะไร?",
        "options": ["แม่น้ำไนล์", "แม่น้ำแอมะซอน", "แม่น้ำแยงซี", "แม่น้ำคงคา"],
        "answer": 1
    },
    {
        "title": "สัตว์ที่วางไข่คือสัตว์ชนิดใด?",
        "options": ["แมว", "นก", "วาฬ", "สุนัข"],
        "answer": 2
    },
    {
        "title": "ในเรื่อง 'พระอภัยมณี' เครื่องดนตรีชนิดใดที่พระอภัยใช้?",
        "options": ["ขลุ่ย", "ซอ", "พิณ", "กลอง"],
        "answer": 1
    }
]
